snx_util/downloader.py
snx_util-0.1.0.dist-info/WHEEL
snx_util-0.1.0.dist-info/METADATA
snx_util-0.1.0.dist-info/RECORD
