Metadata-Version: 2.1
Name: snx-util
Version: 0.1.0
Summary: 
Author: supernovalx
Author-email: hoanganhgo9@gmail.com
Requires-Python: >=3.8,<4.0
Classifier: Programming Language :: Python :: 3
Classifier: Programming Language :: Python :: 3.10
Classifier: Programming Language :: Python :: 3.8
Classifier: Programming Language :: Python :: 3.9
Requires-Dist: requests (>=2.28.1,<3.0.0)
Requires-Dist: tqdm (>=4.64.0,<5.0.0)
